ansys/api/edb/VERSION
ansys/api/edb/__init__.py
ansys/api/edb/py.typed
ansys/api/edb/v1/__init__.py
ansys/api/edb/v1/arc_data.proto
ansys/api/edb/v1/arc_data_pb2.py
ansys/api/edb/v1/arc_data_pb2.pyi
ansys/api/edb/v1/arc_data_pb2_grpc.py
ansys/api/edb/v1/arc_data_pb2_grpc.pyi
ansys/api/edb/v1/board_bend_def.proto
ansys/api/edb/v1/board_bend_def_pb2.py
ansys/api/edb/v1/board_bend_def_pb2.pyi
ansys/api/edb/v1/board_bend_def_pb2_grpc.py
ansys/api/edb/v1/board_bend_def_pb2_grpc.pyi
ansys/api/edb/v1/bondwire.proto
ansys/api/edb/v1/bondwire_def.proto
ansys/api/edb/v1/bondwire_def_pb2.py
ansys/api/edb/v1/bondwire_def_pb2.pyi
ansys/api/edb/v1/bondwire_def_pb2_grpc.py
ansys/api/edb/v1/bondwire_def_pb2_grpc.pyi
ansys/api/edb/v1/bondwire_pb2.py
ansys/api/edb/v1/bondwire_pb2.pyi
ansys/api/edb/v1/bondwire_pb2_grpc.py
ansys/api/edb/v1/bondwire_pb2_grpc.pyi
ansys/api/edb/v1/bundle_term.proto
ansys/api/edb/v1/bundle_term_pb2.py
ansys/api/edb/v1/bundle_term_pb2.pyi
ansys/api/edb/v1/bundle_term_pb2_grpc.py
ansys/api/edb/v1/bundle_term_pb2_grpc.pyi
ansys/api/edb/v1/cell.proto
ansys/api/edb/v1/cell_instance.proto
ansys/api/edb/v1/cell_instance_pb2.py
ansys/api/edb/v1/cell_instance_pb2.pyi
ansys/api/edb/v1/cell_instance_pb2_grpc.py
ansys/api/edb/v1/cell_instance_pb2_grpc.pyi
ansys/api/edb/v1/cell_pb2.py
ansys/api/edb/v1/cell_pb2.pyi
ansys/api/edb/v1/cell_pb2_grpc.py
ansys/api/edb/v1/cell_pb2_grpc.pyi
ansys/api/edb/v1/circle.proto
ansys/api/edb/v1/circle_pb2.py
ansys/api/edb/v1/circle_pb2.pyi
ansys/api/edb/v1/circle_pb2_grpc.py
ansys/api/edb/v1/circle_pb2_grpc.pyi
ansys/api/edb/v1/component_def.proto
ansys/api/edb/v1/component_def_pb2.py
ansys/api/edb/v1/component_def_pb2.pyi
ansys/api/edb/v1/component_def_pb2_grpc.py
ansys/api/edb/v1/component_def_pb2_grpc.pyi
ansys/api/edb/v1/component_group.proto
ansys/api/edb/v1/component_group_pb2.py
ansys/api/edb/v1/component_group_pb2.pyi
ansys/api/edb/v1/component_group_pb2_grpc.py
ansys/api/edb/v1/component_group_pb2_grpc.pyi
ansys_api_edb-1.0.10.dist-info/LICENCE
ansys_api_edb-1.0.10.dist-info/METADATA
ansys_api_edb-1.0.10.dist-info/WHEEL
ansys_api_edb-1.0.10.dist-info/entry_points.txt
ansys_api_edb-1.0.10.dist-info/top_level.txt
ansys_api_edb-1.0.10.dist-info/RECORD
