Metadata-Version: 2.1
Name: ansys-api-edb
Version: 1.0.10
Summary: Autogenerated Python gRPC interface package for ansys-api-edb, built on 16:58:31 on 23 October 2024
Home-page: https://github.com/ansys/ansys-api-edb
Author: ANSYS, Inc.
Author-email: pyansys.core@ansys.com
Maintainer: ANSYS, Inc.
Maintainer-email: pyansys.core@ansys.com
License: MIT
Project-URL: Documentation, https://github.com/ansys/ansys-api-edb/#readme
Project-URL: Source, https://github.com/ansys/ansys-api-edb/
Project-URL: Tracker, https://github.com/ansys/ansys-api-edb/issues/
Requires-Python: >=3.7
License-File: LICENCE
Requires-Dist: grpcio>=1.44
Requires-Dist: protobuf<5,>=3.19.3
